[
  {
    "inputs": [
      {
        "internalType": "address",
        "name": "_stakingRouter",
        "type": "address"
      }
    ],
    "stateMutability": "nonpayable",
    "type": "constructor"
  },
  {
    "inputs": [],
    "name": "AlreadyRegistered",
    "type": "error"
  },
  {
    "inputs": [],
    "name": "InvalidReferrer",
    "type": "error"
  },
  {
    "inputs": [],
    "name": "NoCommissionToClaim",
    "type": "error"
  },
  {
    "inputs": [],
    "name": "SelfReferralNotAllowed",
    "type": "error"
  },
  {
    "inputs": [],
    "name": "TransferFailed",
    "type": "error"
  },
  {
    "inputs": [],
    "name": "Unauthorized",
    "type": "error"
  },
  {
    "inputs": [],
    "name": "ZeroAddress",
    "type": "error"
  },
  {
    "anonymous": false,
    "inputs": [
      {
        "indexed": true,
        "internalType": "address",
        "name": "user",
        "type": "address"
      },
      {
        "indexed": false,
        "internalType": "uint256",
        "name": "amount",
        "type": "uint256"
      }
    ],
    "name": "CommissionClaimed",
    "type": "event"
  },
  {
    "anonymous": false,
    "inputs": [
      {
        "indexed": true,
        "internalType": "address",
        "name": "referrer",
        "type": "address"
      },
      {
        "indexed": true,
        "internalType": "address",
        "name": "referee",
        "type": "address"
      },
      {
        "indexed": false,
        "internalType": "uint256",
        "name": "amount",
        "type": "uint256"
      }
    ],
    "name": "CommissionEarned",
    "type": "event"
  },
  {
    "anonymous": false,
    "inputs": [
      {
        "indexed": true,
        "internalType": "address",
        "name": "user",
        "type": "address"
      },
      {
        "indexed": true,
        "internalType": "address",
        "name": "referrer",
        "type": "address"
      }
    ],
    "name": "ReferralRegistered",
    "type": "event"
  },
  {
    "anonymous": false,
    "inputs": [
      {
        "indexed": true,
        "internalType": "address",
        "name": "oldRouter",
        "type": "address"
      },
      {
        "indexed": true,
        "internalType": "address",
        "name": "newRouter",
        "type": "address"
      }
    ],
    "name": "StakingRouterUpdated",
    "type": "event"
  },
  {
    "anonymous": false,
    "inputs": [
      {
        "indexed": true,
        "internalType": "address",
        "name": "user",
        "type": "address"
      },
      {
        "indexed": false,
        "internalType": "uint256",
        "name": "oldTier",
        "type": "uint256"
      },
      {
        "indexed": false,
        "internalType": "uint256",
        "name": "newTier",
        "type": "uint256"
      }
    ],
    "name": "TierUpgraded",
    "type": "event"
  },
  {
    "anonymous": false,
    "inputs": [
      {
        "indexed": true,
        "internalType": "address",
        "name": "user",
        "type": "address"
      },
      {
        "indexed": false,
        "internalType": "uint256",
        "name": "xpAmount",
        "type": "uint256"
      }
    ],
    "name": "XPEarned",
    "type": "event"
  },
  {
    "inputs": [],
    "name": "BP_DIVISOR",
    "outputs": [
      {
        "internalType": "uint256",
        "name": "",
        "type": "uint256"
      }
    ],
    "stateMutability": "view",
    "type": "function"
  },
  {
    "inputs": [],
    "name": "COMMISSION_BRONZE",
    "outputs": [
      {
        "internalType": "uint256",
        "name": "",
        "type": "uint256"
      }
    ],
    "stateMutability": "view",
    "type": "function"
  },
  {
    "inputs": [],
    "name": "COMMISSION_GOLD",
    "outputs": [
      {
        "internalType": "uint256",
        "name": "",
        "type": "uint256"
      }
    ],
    "stateMutability": "view",
    "type": "function"
  },
  {
    "inputs": [],
    "name": "COMMISSION_PLATINUM",
    "outputs": [
      {
        "internalType": "uint256",
        "name": "",
        "type": "uint256"
      }
    ],
    "stateMutability": "view",
    "type": "function"
  },
  {
    "inputs": [],
    "name": "COMMISSION_SILVER",
    "outputs": [
      {
        "internalType": "uint256",
        "name": "",
        "type": "uint256"
      }
    ],
    "stateMutability": "view",
    "type": "function"
  },
  {
    "inputs": [],
    "name": "COMMISSION_STARTER",
    "outputs": [
      {
        "internalType": "uint256",
        "name": "",
        "type": "uint256"
      }
    ],
    "stateMutability": "view",
    "type": "function"
  },
  {
    "inputs": [],
    "name": "TIER_BRONZE",
    "outputs": [
      {
        "internalType": "uint256",
        "name": "",
        "type": "uint256"
      }
    ],
    "stateMutability": "view",
    "type": "function"
  },
  {
    "inputs": [],
    "name": "TIER_GOLD",
    "outputs": [
      {
        "internalType": "uint256",
        "name": "",
        "type": "uint256"
      }
    ],
    "stateMutability": "view",
    "type": "function"
  },
  {
    "inputs": [],
    "name": "TIER_PLATINUM",
    "outputs": [
      {
        "internalType": "uint256",
        "name": "",
        "type": "uint256"
      }
    ],
    "stateMutability": "view",
    "type": "function"
  },
  {
    "inputs": [],
    "name": "TIER_SILVER",
    "outputs": [
      {
        "internalType": "uint256",
        "name": "",
        "type": "uint256"
      }
    ],
    "stateMutability": "view",
    "type": "function"
  },
  {
    "inputs": [],
    "name": "TIER_STARTER",
    "outputs": [
      {
        "internalType": "uint256",
        "name": "",
        "type": "uint256"
      }
    ],
    "stateMutability": "view",
    "type": "function"
  },
  {
    "inputs": [],
    "name": "claimCommission",
    "outputs": [],
    "stateMutability": "nonpayable",
    "type": "function"
  },
  {
    "inputs": [
      {
        "internalType": "uint256",
        "name": "amount",
        "type": "uint256"
      }
    ],
    "name": "emergencyWithdraw",
    "outputs": [],
    "stateMutability": "nonpayable",
    "type": "function"
  },
  {
    "inputs": [
      {
        "internalType": "address",
        "name": "user",
        "type": "address"
      }
    ],
    "name": "getCommissionRate",
    "outputs": [
      {
        "internalType": "uint256",
        "name": "",
        "type": "uint256"
      }
    ],
    "stateMutability": "view",
    "type": "function"
  },
  {
    "inputs": [
      {
        "internalType": "address",
        "name": "user",
        "type": "address"
      }
    ],
    "name": "getNextTierRequirements",
    "outputs": [
      {
        "internalType": "uint256",
        "name": "refNeeded",
        "type": "uint256"
      },
      {
        "internalType": "uint256",
        "name": "nextTier",
        "type": "uint256"
      }
    ],
    "stateMutability": "view",
    "type": "function"
  },
  {
    "inputs": [
      {
        "internalType": "address",
        "name": "user",
        "type": "address"
      }
    ],
    "name": "getReferralCount",
    "outputs": [
      {
        "internalType": "uint256",
        "name": "",
        "type": "uint256"
      }
    ],
    "stateMutability": "view",
    "type": "function"
  },
  {
    "inputs": [
      {
        "internalType": "address",
        "name": "user",
        "type": "address"
      }
    ],
    "name": "getReferrals",
    "outputs": [
      {
        "internalType": "address[]",
        "name": "",
        "type": "address[]"
      }
    ],
    "stateMutability": "view",
    "type": "function"
  },
  {
    "inputs": [
      {
        "internalType": "address",
        "name": "user",
        "type": "address"
      }
    ],
    "name": "getReferrer",
    "outputs": [
      {
        "internalType": "address",
        "name": "",
        "type": "address"
      }
    ],
    "stateMutability": "view",
    "type": "function"
  },
  {
    "inputs": [
      {
        "internalType": "address",
        "name": "user",
        "type": "address"
      }
    ],
    "name": "getTierName",
    "outputs": [
      {
        "internalType": "string",
        "name": "",
        "type": "string"
      }
    ],
    "stateMutability": "view",
    "type": "function"
  },
  {
    "inputs": [
      {
        "internalType": "address",
        "name": "user",
        "type": "address"
      }
    ],
    "name": "getUserData",
    "outputs": [
      {
        "components": [
          {
            "internalType": "address",
            "name": "referrer",
            "type": "address"
          },
          {
            "internalType": "uint256",
            "name": "referralCount",
            "type": "uint256"
          },
          {
            "internalType": "uint256",
            "name": "totalCommission",
            "type": "uint256"
          },
          {
            "internalType": "uint256",
            "name": "claimableCommission",
            "type": "uint256"
          },
          {
            "internalType": "uint256",
            "name": "withdrawnCommission",
            "type": "uint256"
          },
          {
            "internalType": "uint256",
            "name": "xpPoints",
            "type": "uint256"
          },
          {
            "internalType": "uint256",
            "name": "tier",
            "type": "uint256"
          },
          {
            "internalType": "bool",
            "name": "isRegistered",
            "type": "bool"
          }
        ],
        "internalType": "struct ReferralSystem.UserData",
        "name": "",
        "type": "tuple"
      }
    ],
    "stateMutability": "view",
    "type": "function"
  },
  {
    "inputs": [
      {
        "internalType": "address",
        "name": "user",
        "type": "address"
      }
    ],
    "name": "getUserStats",
    "outputs": [
      {
        "internalType": "uint256",
        "name": "referralCount",
        "type": "uint256"
      },
      {
        "internalType": "uint256",
        "name": "tier",
        "type": "uint256"
      },
      {
        "internalType": "string",
        "name": "tierName",
        "type": "string"
      },
      {
        "internalType": "uint256",
        "name": "commissionRate",
        "type": "uint256"
      },
      {
        "internalType": "uint256",
        "name": "totalEarned",
        "type": "uint256"
      },
      {
        "internalType": "uint256",
        "name": "claimable",
        "type": "uint256"
      },
      {
        "internalType": "uint256",
        "name": "withdrawn",
        "type": "uint256"
      },
      {
        "internalType": "uint256",
        "name": "xpPoints",
        "type": "uint256"
      }
    ],
    "stateMutability": "view",
    "type": "function"
  },
  {
    "inputs": [
      {
        "internalType": "address",
        "name": "user",
        "type": "address"
      }
    ],
    "name": "isRegistered",
    "outputs": [
      {
        "internalType": "bool",
        "name": "",
        "type": "bool"
      }
    ],
    "stateMutability": "view",
    "type": "function"
  },
  {
    "inputs": [],
    "name": "owner",
    "outputs": [
      {
        "internalType": "address",
        "name": "",
        "type": "address"
      }
    ],
    "stateMutability": "view",
    "type": "function"
  },
  {
    "inputs": [
      {
        "internalType": "address",
        "name": "referee",
        "type": "address"
      },
      {
        "internalType": "uint256",
        "name": "rewardAmount",
        "type": "uint256"
      }
    ],
    "name": "recordCommission",
    "outputs": [],
    "stateMutability": "payable",
    "type": "function"
  },
  {
    "inputs": [
      {
        "internalType": "address",
        "name": "",
        "type": "address"
      },
      {
        "internalType": "uint256",
        "name": "",
        "type": "uint256"
      }
    ],
    "name": "referrals",
    "outputs": [
      {
        "internalType": "address",
        "name": "",
        "type": "address"
      }
    ],
    "stateMutability": "view",
    "type": "function"
  },
  {
    "inputs": [
      {
        "internalType": "address",
        "name": "referrer",
        "type": "address"
      }
    ],
    "name": "registerReferral",
    "outputs": [],
    "stateMutability": "nonpayable",
    "type": "function"
  },
  {
    "inputs": [
      {
        "internalType": "address",
        "name": "newRouter",
        "type": "address"
      }
    ],
    "name": "setStakingRouter",
    "outputs": [],
    "stateMutability": "nonpayable",
    "type": "function"
  },
  {
    "inputs": [],
    "name": "stakingRouter",
    "outputs": [
      {
        "internalType": "address",
        "name": "",
        "type": "address"
      }
    ],
    "stateMutability": "view",
    "type": "function"
  },
  {
    "inputs": [],
    "name": "totalCommissionsPaid",
    "outputs": [
      {
        "internalType": "uint256",
        "name": "",
        "type": "uint256"
      }
    ],
    "stateMutability": "view",
    "type": "function"
  },
  {
    "inputs": [],
    "name": "totalReferrals",
    "outputs": [
      {
        "internalType": "uint256",
        "name": "",
        "type": "uint256"
      }
    ],
    "stateMutability": "view",
    "type": "function"
  },
  {
    "inputs": [],
    "name": "totalUsers",
    "outputs": [
      {
        "internalType": "uint256",
        "name": "",
        "type": "uint256"
      }
    ],
    "stateMutability": "view",
    "type": "function"
  },
  {
    "inputs": [
      {
        "internalType": "address",
        "name": "newOwner",
        "type": "address"
      }
    ],
    "name": "transferOwnership",
    "outputs": [],
    "stateMutability": "nonpayable",
    "type": "function"
  },
  {
    "inputs": [
      {
        "internalType": "address",
        "name": "",
        "type": "address"
      }
    ],
    "name": "users",
    "outputs": [
      {
        "internalType": "address",
        "name": "referrer",
        "type": "address"
      },
      {
        "internalType": "uint256",
        "name": "referralCount",
        "type": "uint256"
      },
      {
        "internalType": "uint256",
        "name": "totalCommission",
        "type": "uint256"
      },
      {
        "internalType": "uint256",
        "name": "claimableCommission",
        "type": "uint256"
      },
      {
        "internalType": "uint256",
        "name": "withdrawnCommission",
        "type": "uint256"
      },
      {
        "internalType": "uint256",
        "name": "xpPoints",
        "type": "uint256"
      },
      {
        "internalType": "uint256",
        "name": "tier",
        "type": "uint256"
      },
      {
        "internalType": "bool",
        "name": "isRegistered",
        "type": "bool"
      }
    ],
    "stateMutability": "view",
    "type": "function"
  },
  {
    "stateMutability": "payable",
    "type": "receive"
  }
]